{
  "slide_number": 5,
  "text_annotations": [
    {
      "annotation_id": "annot_1",
      "bone_name": "Bony Pelvis",
      "subbone_name": "Internal lip",
      "text_content": "Internal lip",
      "text_box": {
        "x": 6241064.0,
        "y": 1875464.0,
        "width": 636362.0,
        "height": 215444.0,
        "rotation_emu": 0.0,
        "shape_id": "206"
      },
      "has_hyperlink": false,
      "hyperlink": {},
      "pointer_lines": [
        {
          "line_id": "line_1",
          "kind": "connector",
          "start_point": {
            "x": 6877426.0,
            "y": 1983186.0
          },
          "end_point": {
            "x": 7460626.0,
            "y": 1983186.0
          },
          "style": {
            "width": 9525,
            "arrow_head": "none"
          },
          "shape_id": "207",
          "bbox": {
            "x": 6877426.0,
            "y": 1983186.0,
            "width": 583200.0,
            "height": 0.0,
            "rotation_emu": 0.0
          }
        }
      ],
      "target_regions": [
        {
          "x": 7464000.0,
          "y": 1982000.0
        }
      ]
    },
    {
      "annotation_id": "annot_2",
      "bone_name": "Bony Pelvis",
      "subbone_name": "External lip",
      "text_content": "External lip",
      "text_box": {
        "x": 5421812.0,
        "y": 1875464.0,
        "width": 651140.0,
        "height": 215444.0,
        "rotation_emu": 0.0,
        "shape_id": "208"
      },
      "has_hyperlink": false,
      "hyperlink": {},
      "pointer_lines": [
        {
          "line_id": "line_2",
          "kind": "connector",
          "start_point": {
            "x": 4905812.0,
            "y": 1983186.0
          },
          "end_point": {
            "x": 5421812.0,
            "y": 1983186.0
          },
          "style": {
            "width": 9525,
            "arrow_head": "none"
          },
          "shape_id": "209",
          "bbox": {
            "x": 4905812.0,
            "y": 1983186.0,
            "width": 516000.0,
            "height": 0.0,
            "rotation_emu": 0.0
          }
        }
      ],
      "target_regions": [
        {
          "x": 4904000.0,
          "y": 1982000.0
        }
      ]
    }
  ],
  "total_text_annotations": 2,
  "config": {
    "padding_emu": 4000.0,
    "snap_emu": 8000.0
  }
}